alignak_backend_client/__init__.py
alignak_backend_client/backend_client.py
alignak_backend_client/client.py
alignak_backend_client/examples/__init__.py
alignak_backend_client-1.4.2.dist-info/METADATA
alignak_backend_client-1.4.2.dist-info/RECORD
alignak_backend_client-1.4.2.dist-info/WHEEL
alignak_backend_client-1.4.2.dist-info/entry_points.txt
alignak_backend_client-1.4.2.dist-info/top_level.txt
