Metadata-Version: 2.1
Name: alignak-backend-client
Version: 1.4.2
Summary: Alignak REST backend client library
Requires-Dist: requests
Requires-Dist: future
